scripts/jp2_to_zarr.py
scripts/lsm_tiff_to_zarr.py
scripts/utils.py
linc_convert-0.0.1.dist-info/METADATA
linc_convert-0.0.1.dist-info/WHEEL
linc_convert-0.0.1.dist-info/licenses/LICENSE
linc_convert-0.0.1.dist-info/RECORD
